COPYING
LICENCE
MANIFEST.in
NEWS
README
bootstrap.py
distribute_setup.py
pavement.py
setup.cfg
setup.py
docs/html/appendix_a.html
docs/html/example.html
docs/html/genindex.html
docs/html/glossary.html
docs/html/index.html
docs/html/licence.html
docs/html/news.html
docs/html/py-modindex.html
docs/html/search.html
docs/html/searchindex.js
docs/html/todo.html
docs/html/_images/graphviz-5381f78157b62f0257700184955e676c892b5ce9.png
docs/html/_images/graphviz-5381f78157b62f0257700184955e676c892b5ce9.png.map
docs/html/_images/graphviz-750b7414a5bd14c97d1dd5ec839498927391b3b8.png
docs/html/_images/graphviz-750b7414a5bd14c97d1dd5ec839498927391b3b8.png.map
docs/html/_images/inheritance-05067d1e6db9ac4e0206ad3133184a4d3ec1227a.png
docs/html/_images/inheritance-05067d1e6db9ac4e0206ad3133184a4d3ec1227a.png.map
docs/html/_images/inheritance-4ccc8da48f2b20b7fae1716ca51f482553d506f3.png
docs/html/_images/inheritance-4ccc8da48f2b20b7fae1716ca51f482553d506f3.png.map
docs/html/_images/inheritance-55a8877ac111369dd29bea2b145dab43a3a45724.png
docs/html/_images/inheritance-55a8877ac111369dd29bea2b145dab43a3a45724.png.map
docs/html/_images/inheritance-62bbf8a5c7f1c185e10dcf99b51420965d3fdbe2.png
docs/html/_images/inheritance-62bbf8a5c7f1c185e10dcf99b51420965d3fdbe2.png.map
docs/html/_images/inheritance-84851eb52388abb681fea48b668a403d0f9c6b62.png
docs/html/_images/inheritance-84851eb52388abb681fea48b668a403d0f9c6b62.png.map
docs/html/_images/inheritance-a0e5263762a02bcb118b303b96f89c7cde60b632.png
docs/html/_images/inheritance-a0e5263762a02bcb118b303b96f89c7cde60b632.png.map
docs/html/_images/inheritance-aed85c1899ca42555ca6bac0b67a3c4e66727691.png
docs/html/_images/inheritance-aed85c1899ca42555ca6bac0b67a3c4e66727691.png.map
docs/html/_images/inheritance-c97e46288e44a2d239ad66230671353cb9e7f3e5.png
docs/html/_images/inheritance-c97e46288e44a2d239ad66230671353cb9e7f3e5.png.map
docs/html/_images/inheritance-cafb4da47d02f80b901add23e771315f59fee7e8.png
m4us.egg-info/PKG-INFO
m4us.egg-info/SOURCES.txt
m4us.egg-info/dependency_links.txt
m4us.egg-info/not-zip-safe
m4us.egg-info/requires.txt
m4us.egg-info/top_level.txt
