Metadata-Version: 1.1
Name: m4us
Version: 0.3.0
Summary: A pythonic coroutine-based concurrent programming framework inspired by Kamaelia.
Home-page: http://pypi.python.org/pypi/m4us
Author: Krys Lawrence
Author-email: m4us@krys.ca
License: UNKNOWN
Download-URL: http://pypi.python.org/pypi/m4us#downloads
Keywords: m4us concurrency coroutine kamaelia framework message
Platform: UNKNOWN
Classifier: Development Status :: 3 - Alpha
Classifier: Intended Audience :: Developers
Classifier: Intended Audience :: Information Technology
Classifier: Intended Audience :: System Administrators
Classifier: License :: OSI Approved :: GNU Affero General Public License v3
Classifier: Natural Language :: English
Classifier: Operating System :: OS Independent
Classifier: Programming Language :: Python :: 2 :: Only
Classifier: Programming Language :: Python :: 2.6
Classifier: Programming Language :: Python :: 2.7
Classifier: Topic :: Software Development :: Libraries :: Python Modules
Classifier: Topic :: Software Development :: Libraries :: Application Frameworks
Requires: zope.interface (>=3.8.0,<3.8.99)
Requires: decorator (>=3.3.2,<3.3.99)
Requires: unittest2 (>=0.5.1,<0.5.99)
Requires: mock (>=0.8.0,<0.8.99)
Provides: m4us
